fastccc/0.01index_mat.npy
fastccc/__init__.py
fastccc/build_reference.py
fastccc/cauchy_combine.py
fastccc/ccc_utils.py
fastccc/core.py
fastccc/dist_complex.py
fastccc/dist_iid_set.py
fastccc/dist_lr.py
fastccc/distrib.py
fastccc/distrib_digit.py
fastccc/hk_genes.py
fastccc/infer_query.py
fastccc/preproc_utils.py
fastccc/preprocess.py
fastccc/score.py
fastccc/visualize.py
fastccc-0.1.1.dist-info/METADATA
fastccc-0.1.1.dist-info/WHEEL
fastccc-0.1.1.dist-info/licenses/LICENSE
fastccc-0.1.1.dist-info/RECORD
