Metadata-Version: 2.4
Name: fastccc
Version: 0.1.1
Summary: A permutation-free framework for scalable, robust, and reference-based cell-cell communication analysis in single cell transcriptomics studies.
License-File: LICENSE
Author: Svvord
Author-email: cchousiyu@163.com
Requires-Python: >=3.11,<3.13
Classifier: Programming Language :: Python :: 3
Classifier: Programming Language :: Python :: 3.11
Classifier: Programming Language :: Python :: 3.12
Requires-Dist: gseapy (>=1.1.4,<2.0.0)
Requires-Dist: loguru (>=0.7.2,<0.8.0)
Requires-Dist: numpy (>=1.24,<2.0)
Requires-Dist: openpyxl (>=3.1.5,<4.0.0)
Requires-Dist: pandas (>=2.2.3,<3.0.0)
Requires-Dist: psutil (>=6.1.1,<7.0.0)
Requires-Dist: scanpy (>=1.10.3,<2.0.0)
Requires-Dist: scipy (>=1.14.1,<2.0.0)
